setup.cfg
setup.py
zimsoap/__init__.py
zimsoap/client.py
zimsoap/utils.py
zimsoap/zobjects.py
zimsoap.egg-info/PKG-INFO
zimsoap.egg-info/SOURCES.txt
zimsoap.egg-info/dependency_links.txt
zimsoap.egg-info/pbr.json
zimsoap.egg-info/requires.txt
zimsoap.egg-info/top_level.txt