Metadata-Version: 1.0
Name: zimsoap
Version: 0.4.2
Summary: A high-level library to access programaticaly Zimbra                    SOAP API features
Home-page: https://github.com/oasiswork/zimsoap/
Author: Jocelyn Delalande
Author-email: jdelalande@oasiswork.fr
License: UNKNOWN
Platform: UNKNOWN
